pracsvkm/__init__.py
pracsvkm/main.py
svkmprac-0.1.0.dist-info/METADATA
svkmprac-0.1.0.dist-info/WHEEL
svkmprac-0.1.0.dist-info/top_level.txt
svkmprac-0.1.0.dist-info/RECORD
