Metadata-Version: 2.4
Name: svkmprac
Version: 0.1.0
Summary: Add your description here
Requires-Python: >=3.13
Requires-Dist: setuptools>=80.9.0
Requires-Dist: twine>=6.2.0
